{"stats":{"minecraft:killed_by":{"minecraft:phantom":1,"minecraft:skeleton":1,"minecraft:zombie_villager":1,"minecraft:creeper":3,"minecraft:iron_golem":1,"minecraft:drowned":1,"minecraft:husk":1,"minecraft:zombie":4},"minecraft:used":{"minecraft:diamond_helmet":3,"minecraft:end_stone":494,"minecraft:kelp":32,"minecraft:white_banner":7,"minecraft:shulker_box":122,"minecraft:diamond_sword":2010,"minecraft:cobbled_deepslate_slab":12,"minecraft:campfire":25,"minecraft:wheat_seeds":521,"minecraft:red_shulker_box":45,"minecraft:glass":1780,"minecraft:ender_eye":18,"minecraft:decorated_pot":4,"minecraft:yellow_carpet":27,"minecraft:damaged_anvil":3,"minecraft:detector_rail":5,"minecraft:coal_ore":14,"minecraft:crafter":11,"minecraft:spruce_slab":25,"minecraft:diamond_axe":5702,"minecraft:white_carpet":242,"minecraft:poppy":81,"minecraft:end_stone_bricks":3,"minecraft:snowball":103,"minecraft:moss_block":1,"minecraft:hopper_minecart":5,"minecraft:calcite":2,"minecraft:bow":1540,"minecraft:cobbled_deepslate":187,"minecraft:mossy_cobblestone":29,"minecraft:podzol":3,"minecraft:dragon_head":1,"minecraft:fletching_table":31,"minecraft:anvil":21,"minecraft:spruce_fence_gate":9,"minecraft:sand":3,"minecraft:redstone_block":2,"minecraft:wind_charge":16,"minecraft:lodestone":1,"minecraft:glow_ink_sac":4,"minecraft:shears":287,"minecraft:bucket":442,"minecraft:warped_nylium":7,"minecraft:flower_pot":2,"minecraft:diamond_block":2,"minecraft:grass_block":7,"minecraft:nether_bricks":590,"minecraft:string":176,"minecraft:emerald_block":175,"minecraft:shield":135,"minecraft:deepslate":41,"minecraft:iron_pickaxe":490,"minecraft:andesite":67,"minecraft:bamboo":46,"minecraft:waxed_copper_block":1,"minecraft:firework_rocket":2972,"minecraft:iron_sword":915,"minecraft:tnt":301,"minecraft:golden_carrot":96,"minecraft:stone_brick_slab":169,"minecraft:cookie":3,"minecraft:stone_bricks":1185,"minecraft:minecart":148,"minecraft:packed_ice":764,"minecraft:smooth_stone":2,"minecraft:diorite":26,"minecraft:redstone":101,"minecraft:wooden_pickaxe":20,"minecraft:pumpkin_seeds":10,"minecraft:white_stained_glass":70,"minecraft:spruce_door":1,"minecraft:diamond_leggings":3,"minecraft:cobblestone":1114,"minecraft:diamond_chestplate":108,"minecraft:stone":1633,"minecraft:golden_apple":18,"minecraft:axolotl_bucket":13,"minecraft:chain":46,"minecraft:crafting_table":66,"minecraft:spruce_sign":81,"minecraft:sculk":7,"minecraft:iron_chestplate":3,"minecraft:spruce_trapdoor":120,"minecraft:red_mushroom":2,"minecraft:potion":15,"minecraft:tuff_bricks":1,"minecraft:baked_potato":120,"minecraft:scaffolding":168,"minecraft:smoker":2,"minecraft:purple_carpet":3,"minecraft:melon_slice":3,"minecraft:soul_soil":5,"minecraft:spruce_log":83,"minecraft:pumpkin":15,"minecraft:water_bucket":389,"minecraft:soul_sand":46,"minecraft:bread":12,"minecraft:torch":926,"minecraft:black_bed":13,"minecraft:pink_dye":1,"minecraft:cobblestone_stairs":8,"minecraft:gravel":120,"minecraft:cake":1,"minecraft:chipped_anvil":2,"minecraft:beacon":4,"minecraft:cooked_chicken":87,"minecraft:white_wool":56,"minecraft:comparator":28,"minecraft:sculk_sensor":1,"minecraft:amethyst_block":2,"minecraft:chest":200,"minecraft:enchanting_table":4,"minecraft:beef":1,"minecraft:sandstone":68,"minecraft:iron_axe":769,"minecraft:leaf_litter":4,"minecraft:repeater":43,"minecraft:stone_slab":1626,"minecraft:ominous_trial_key":4,"minecraft:spruce_pressure_plate":32,"minecraft:iron_block":341,"minecraft:netherite_shovel":16128,"minecraft:netherite_axe":16,"minecraft:potato":858,"minecraft:sticky_piston":1,"minecraft:glass_bottle":14,"minecraft:jungle_planks":15,"minecraft:lantern":12,"minecraft:netherite_pickaxe":42838,"minecraft:cooked_porkchop":386,"minecraft:granite":18,"minecraft:iron_shovel":115,"minecraft:copper_ore":2,"minecraft:pale_oak_sign":3,"minecraft:firefly_bush":2,"minecraft:cracked_stone_bricks":3,"minecraft:crimson_sign":6,"minecraft:smithing_table":3,"minecraft:blue_shulker_box":75,"minecraft:warped_roots":1,"minecraft:grindstone":6,"minecraft:nether_wart":46,"minecraft:blackstone":14,"minecraft:pumpkin_pie":1,"minecraft:purpur_block":14,"minecraft:stone_pickaxe":50,"minecraft:stone_pressure_plate":1,"minecraft:netherrack":4082,"minecraft:spruce_boat":44,"minecraft:lingering_potion":1,"minecraft:diamond_shovel":4731,"minecraft:deepslate_diamond_ore":2,"minecraft:writable_book":50,"minecraft:experience_bottle":1,"minecraft:bone_meal":1496,"minecraft:white_shulker_box":58,"minecraft:dark_oak_planks":19,"minecraft:glowstone":35,"minecraft:dirt":789,"minecraft:purple_shulker_box":46,"minecraft:obsidian":175,"minecraft:spruce_leaves":172,"minecraft:spruce_planks":564,"minecraft:basalt":523,"minecraft:rail":1355,"minecraft:iron_bars":17,"minecraft:nether_brick_fence":1,"minecraft:lectern":536,"minecraft:powered_rail":203,"minecraft:splash_potion":8,"minecraft:deepslate_tiles":1595,"minecraft:totem_of_undying":11,"minecraft:sugar_cane":38,"minecraft:dropper":1,"minecraft:iron_ore":1,"minecraft:ice":137,"minecraft:trial_key":11,"minecraft:stone_axe":732,"minecraft:spruce_fence":523,"minecraft:observer":2,"minecraft:netherite_sword":3550,"minecraft:spruce_stairs":8,"minecraft:light_blue_shulker_box":5,"minecraft:leather_leggings":2,"minecraft:milk_bucket":1,"minecraft:purple_bed":24,"minecraft:closed_eyeblossom":1,"minecraft:elytra":113,"minecraft:bookshelf":70,"minecraft:diamond_pickaxe":12274,"minecraft:ladder":21,"minecraft:crossbow":4,"minecraft:magma_block":2,"minecraft:blast_furnace":1,"minecraft:mossy_stone_bricks":1,"minecraft:spruce_wood":4,"minecraft:brewing_stand":2,"minecraft:piston":259,"minecraft:sweet_berries":9,"minecraft:lava_bucket":24,"minecraft:cobblestone_wall":261,"minecraft:ominous_bottle":8,"minecraft:brown_mushroom":2,"minecraft:large_fern":1,"minecraft:hopper":38,"minecraft:carrot":69,"minecraft:white_bed":105,"minecraft:diamond_boots":4,"minecraft:trident":2,"minecraft:waxed_oxidized_copper":1,"minecraft:iron_hoe":158,"minecraft:cyan_bed":61,"minecraft:turtle_egg":5,"minecraft:wither_skeleton_skull":16,"minecraft:bell":11,"minecraft:smooth_basalt":1,"minecraft:furnace":11,"minecraft:blue_bed":7,"minecraft:fern":1,"minecraft:wooden_hoe":1,"minecraft:lever":127,"minecraft:warped_fungus":1,"minecraft:blue_ice":26,"minecraft:tripwire_hook":60,"minecraft:cobblestone_slab":1540,"minecraft:stone_button":7,"minecraft:spruce_button":14,"minecraft:dragon_egg":1,"minecraft:composter":25,"minecraft:stone_stairs":6,"minecraft:cooked_beef":123,"minecraft:waxed_oxidized_cut_copper":1,"minecraft:ender_chest":128,"minecraft:flint_and_steel":200,"minecraft:redstone_torch":58,"minecraft:spruce_sapling":60,"minecraft:ender_pearl":137},"minecraft:mined":{"minecraft:torch":85,"minecraft:lever":3,"minecraft:spruce_log":4322,"minecraft:nether_quartz_ore":97,"minecraft:chest":45,"minecraft:blue_ice":26,"minecraft:pumpkin":27,"minecraft:netherrack":9054,"minecraft:beacon":3,"minecraft:bone_block":39,"minecraft:waxed_oxidized_cut_copper":2,"minecraft:brown_mushroom":35,"minecraft:spruce_planks":694,"minecraft:attached_pumpkin_stem":2,"minecraft:wither_skeleton_skull":3,"minecraft:sweet_berry_bush":28,"minecraft:large_fern":78,"minecraft:magma_block":893,"minecraft:dark_oak_planks":19,"minecraft:redstone_torch":35,"minecraft:blue_bed":6,"minecraft:tnt":33,"minecraft:waxed_weathered_copper_bulb":1,"minecraft:blackstone":24,"minecraft:anvil":13,"minecraft:grindstone":13,"minecraft:jungle_planks":3,"minecraft:pale_oak_sign":1,"minecraft:campfire":3,"minecraft:gold_block":1,"minecraft:wall_torch":59,"minecraft:fire":171,"minecraft:smithing_table":3,"minecraft:purple_carpet":9,"minecraft:ender_chest":126,"minecraft:deepslate_tiles":63,"minecraft:azalea":1,"minecraft:glass_pane":55,"minecraft:chain":12,"minecraft:spruce_wall_sign":4,"minecraft:stone_slab":745,"minecraft:glass":450,"minecraft:stone_pressure_plate":1,"minecraft:tripwire_hook":4,"minecraft:diamond_block":2,"minecraft:kelp":21,"minecraft:scaffolding":66,"minecraft:brewing_stand":4,"minecraft:clay":425,"minecraft:cyan_bed":39,"minecraft:spruce_stairs":15,"minecraft:fletching_table":31,"minecraft:waxed_copper_door":1,"minecraft:spruce_button":8,"minecraft:crimson_roots":1,"minecraft:jack_o_lantern":1,"minecraft:iron_bars":7,"minecraft:tall_grass":11,"minecraft:waxed_copper_block":9,"minecraft:mossy_stone_bricks":10,"minecraft:cobbled_deepslate_slab":1,"minecraft:twisting_vines":1,"minecraft:tall_dry_grass":4,"minecraft:tripwire":93,"minecraft:water_cauldron":2,"minecraft:shulker_box":124,"minecraft:soul_fire":17,"minecraft:spruce_door":17,"minecraft:sand":3894,"minecraft:seagrass":5,"minecraft:bamboo_sapling":1,"minecraft:spruce_sign":1,"minecraft:lapis_ore":13,"minecraft:black_bed":10,"minecraft:warped_roots":6,"minecraft:vine":9,"minecraft:sea_lantern":1,"minecraft:carrots":28,"minecraft:lectern":533,"minecraft:short_grass":44,"minecraft:sculk_catalyst":1,"minecraft:dirt_path":6,"minecraft:crafting_table":59,"minecraft:flowering_azalea":1,"minecraft:deepslate_redstone_ore":39,"minecraft:leaf_litter":1,"minecraft:redstone_wall_torch":14,"minecraft:coarse_dirt":14,"minecraft:copper_ore":174,"minecraft:waxed_exposed_copper_bulb":1,"minecraft:smooth_stone":2,"minecraft:packed_ice":1312,"minecraft:cave_vines_plant":4,"minecraft:blast_furnace":1,"minecraft:end_rod":6,"minecraft:iron_block":178,"minecraft:yellow_wool":1,"minecraft:white_wall_banner":4,"minecraft:stone_bricks":147,"minecraft:dropper":1,"minecraft:crimson_stem":4,"minecraft:sculk_sensor":2,"minecraft:wheat":273,"minecraft:red_shulker_box":46,"minecraft:white_stained_glass":2,"minecraft:yellow_carpet":6,"minecraft:soul_sand":205,"minecraft:soul_soil":28,"minecraft:enchanting_table":3,"minecraft:mossy_cobblestone":381,"minecraft:nether_wart":32,"minecraft:big_dripleaf":2,"minecraft:grass_block":4535,"minecraft:stone_brick_slab":6,"minecraft:tuff_bricks":15,"minecraft:white_wool":52,"minecraft:damaged_anvil":3,"minecraft:calcite":2,"minecraft:spruce_slab":18,"minecraft:emerald_block":177,"minecraft:spore_blossom":2,"minecraft:comparator":16,"minecraft:light_blue_wool":1,"minecraft:spruce_wood":27,"minecraft:lodestone":1,"minecraft:smooth_basalt":1,"minecraft:amethyst_block":2,"minecraft:crafter":8,"minecraft:piston_head":1,"minecraft:purple_shulker_box":46,"minecraft:farmland":1,"minecraft:obsidian":370,"minecraft:waxed_oxidized_copper_grate":10,"minecraft:waxed_oxidized_copper":2,"minecraft:cave_vines":6,"minecraft:sandstone":25,"minecraft:melon":183,"minecraft:piston":134,"minecraft:stripped_spruce_log":49,"minecraft:turtle_egg":1,"minecraft:iron_door":6,"minecraft:oak_fence":2,"minecraft:smooth_stone_slab":10,"minecraft:repeater":10,"minecraft:moss_block":36,"minecraft:bamboo":33,"minecraft:nether_brick_fence":12,"minecraft:decorated_pot":18,"minecraft:fern":95,"minecraft:kelp_plant":27,"minecraft:deepslate_diamond_ore":138,"minecraft:potatoes":802,"minecraft:attached_melon_stem":22,"minecraft:warped_stem":2,"minecraft:iron_ore":178,"minecraft:pumpkin_stem":3,"minecraft:nether_sprouts":1,"minecraft:podzol":1569,"minecraft:closed_eyeblossom":2,"minecraft:oak_planks":4,"minecraft:cobblestone":1663,"minecraft:light_gray_stained_glass":1,"minecraft:sugar_cane":365,"minecraft:spruce_fence_gate":10,"minecraft:purpur_pillar":14,"minecraft:spruce_pressure_plate":4,"minecraft:furnace":1,"minecraft:end_stone":551,"minecraft:powered_rail":153,"minecraft:cracked_stone_bricks":6,"minecraft:purple_bed":25,"minecraft:tall_seagrass":1,"minecraft:rail":1189,"minecraft:dirt":9337,"minecraft:cobblestone_wall":185,"minecraft:hopper":32,"minecraft:ladder":12,"minecraft:basalt":631,"minecraft:deepslate":673,"minecraft:snow":244,"minecraft:potted_poppy":1,"minecraft:redstone_ore":7,"minecraft:sculk":31,"minecraft:spawner":2,"minecraft:warped_nylium":54,"minecraft:gravel":710,"minecraft:waxed_copper_grate":2,"minecraft:pale_oak_wall_sign":1,"minecraft:infested_stone_bricks":1,"minecraft:melon_stem":19,"minecraft:twisting_vines_plant":1,"minecraft:purpur_slab":2,"minecraft:white_shulker_box":58,"minecraft:firefly_bush":4,"minecraft:gold_ore":27,"minecraft:chiseled_tuff":1,"minecraft:andesite":494,"minecraft:glowstone":105,"minecraft:purpur_block":15,"minecraft:deepslate_gold_ore":134,"minecraft:ice":452,"minecraft:nether_bricks":242,"minecraft:poppy":4,"minecraft:deepslate_lapis_ore":18,"minecraft:deepslate_iron_ore":121,"minecraft:stone":31194,"minecraft:granite":374,"minecraft:cobblestone_stairs":44,"minecraft:spruce_fence":387,"minecraft:detector_rail":2,"minecraft:coal_ore":661,"minecraft:diorite":458,"minecraft:ancient_debris":1,"minecraft:blue_shulker_box":74,"minecraft:spruce_trapdoor":323,"minecraft:white_bed":64,"minecraft:smoker":1,"minecraft:dragon_wall_head":2,"minecraft:chorus_plant":1,"minecraft:end_stone_bricks":4,"minecraft:composter":49,"minecraft:sculk_vein":23,"minecraft:bookshelf":127,"minecraft:cobbled_deepslate_stairs":1,"minecraft:white_carpet":19,"minecraft:short_dry_grass":1,"minecraft:crimson_nylium":14,"minecraft:glow_lichen":1,"minecraft:polished_blackstone_bricks":3,"minecraft:light_blue_shulker_box":5,"minecraft:observer":1,"minecraft:cobweb":68,"minecraft:spruce_leaves":556,"minecraft:chiseled_tuff_bricks":2,"minecraft:cobbled_deepslate":82,"minecraft:tuff":15,"minecraft:polished_tuff":1,"minecraft:nether_gold_ore":72,"minecraft:polished_andesite":45,"minecraft:cobblestone_slab":73,"minecraft:bell":12,"minecraft:redstone_wire":88,"minecraft:stone_stairs":2},"minecraft:custom":{"minecraft:eat_cake_slice":19,"minecraft:time_since_rest":9953,"minecraft:leave_game":151,"minecraft:boat_one_cm":567831,"minecraft:damage_absorbed":672,"minecraft:time_since_death":1117088,"minecraft:aviate_one_cm":37095471,"minecraft:interact_with_furnace":427,"minecraft:total_world_time":5854072,"minecraft:crouch_one_cm":1993974,"minecraft:raid_win":6,"minecraft:climb_one_cm":113590,"minecraft:deaths":17,"minecraft:interact_with_stonecutter":2,"minecraft:animals_bred":37,"minecraft:minecart_one_cm":133954,"minecraft:traded_with_villager":1702,"minecraft:damage_resisted":11083,"minecraft:damage_blocked_by_shield":17486,"minecraft:interact_with_crafting_table":362,"minecraft:inspect_dropper":49,"minecraft:walk_one_cm":10380638,"minecraft:walk_under_water_one_cm":479482,"minecraft:horse_one_cm":230610,"minecraft:damage_dealt":292327,"minecraft:play_time":5854072,"minecraft:jump":45551,"minecraft:sprint_one_cm":7320960,"minecraft:inspect_hopper":348,"minecraft:fly_one_cm":7893272,"minecraft:walk_on_water_one_cm":454611,"minecraft:interact_with_blast_furnace":38,"minecraft:interact_with_grindstone":43,"minecraft:talked_to_villager":1558,"minecraft:damage_taken":69209,"minecraft:mob_kills":13102,"minecraft:open_shulker_box":900,"minecraft:interact_with_beacon":35,"minecraft:open_enderchest":374,"minecraft:interact_with_brewingstand":32,"minecraft:interact_with_smithing_table":9,"minecraft:sleep_in_bed":153,"minecraft:inspect_dispenser":34,"minecraft:swim_one_cm":478641,"minecraft:pot_flower":1,"minecraft:player_kills":3,"minecraft:enchant_item":103,"minecraft:interact_with_loom":2,"minecraft:drop":4595,"minecraft:interact_with_cartography_table":1,"minecraft:bell_ring":137,"minecraft:open_barrel":161,"minecraft:open_chest":3310,"minecraft:interact_with_smoker":69,"minecraft:fall_one_cm":1893703,"minecraft:tune_noteblock":1,"minecraft:interact_with_anvil":110,"minecraft:sneak_time":522604,"minecraft:raid_trigger":6},"minecraft:crafted":{"minecraft:sandstone":16,"minecraft:firework_rocket":3470,"minecraft:netherite_shovel":1,"minecraft:arrow":192,"minecraft:warped_planks":8,"minecraft:gold_ingot":171,"minecraft:book":2,"minecraft:crimson_planks":16,"minecraft:lever":12,"minecraft:stone_bricks":1520,"minecraft:diamond_pickaxe":6,"minecraft:chest":91,"minecraft:iron_block":2387,"minecraft:bookshelf":61,"minecraft:stone_slab":1422,"minecraft:bow":18,"minecraft:repeater":31,"minecraft:bucket":5,"minecraft:flint_and_steel":4,"minecraft:jungle_planks":20,"minecraft:ladder":15,"minecraft:beacon":1,"minecraft:gray_wool":16,"minecraft:dispenser":12,"minecraft:diamond_shovel":6,"minecraft:crafter":3,"minecraft:white_stained_glass":56,"minecraft:glass":1737,"minecraft:cobblestone_slab":3678,"minecraft:iron_hoe":2,"minecraft:spruce_fence":345,"minecraft:wooden_hoe":1,"minecraft:purple_shulker_box":1,"minecraft:cobbled_deepslate_slab":48,"minecraft:sugar":24,"minecraft:stone_stairs":4,"minecraft:campfire":25,"minecraft:pink_dye":2,"minecraft:comparator":9,"minecraft:hopper_minecart":1,"minecraft:cooked_mutton":6,"minecraft:coal_block":24,"minecraft:spruce_door":3,"minecraft:iron_boots":10,"minecraft:smooth_stone":2,"minecraft:white_wool":597,"minecraft:cooked_beef":103,"minecraft:blue_dye":3,"minecraft:fletching_table":10,"minecraft:spruce_sign":117,"minecraft:iron_bars":16,"minecraft:apple":12,"minecraft:paper":861,"minecraft:furnace":9,"minecraft:iron_ingot":179,"minecraft:diamond_helmet":3,"minecraft:scaffolding":90,"minecraft:tripwire_hook":2,"minecraft:stone":875,"minecraft:tnt":304,"minecraft:blaze_powder":30,"minecraft:diamond_leggings":2,"minecraft:enchanted_book":60,"minecraft:white_shulker_box":1,"minecraft:baked_potato":139,"minecraft:spruce_stairs":4,"minecraft:shield":16,"minecraft:stone_axe":13,"minecraft:observer":15,"minecraft:netherite_pickaxe":3,"minecraft:black_wool":1,"minecraft:name_tag":4,"minecraft:iron_axe":3,"minecraft:piston":8,"minecraft:spruce_button":69,"minecraft:golden_apple":11,"minecraft:spruce_fence_gate":4,"minecraft:diamond_boots":4,"minecraft:smithing_table":1,"minecraft:writable_book":2,"minecraft:powered_rail":72,"minecraft:ender_eye":24,"minecraft:stick":25064,"minecraft:stone_brick_slab":246,"minecraft:compass":6,"minecraft:ender_chest":6,"minecraft:minecart":7,"minecraft:black_dye":1,"minecraft:cooked_porkchop":5,"minecraft:diamond_axe":1,"minecraft:cobblestone_wall":126,"minecraft:air":0,"minecraft:redstone":18,"minecraft:bone_meal":1590,"minecraft:chainmail_boots":3,"minecraft:glass_bottle":9,"minecraft:stone_button":6,"minecraft:yellow_carpet":24,"minecraft:red_dye":2,"minecraft:shulker_box":4,"minecraft:redstone_torch":106,"minecraft:lapis_lazuli":108,"minecraft:coal":27,"minecraft:enchanting_table":1,"minecraft:rail":320,"minecraft:iron_sword":3,"minecraft:shears":3,"minecraft:iron_shovel":1,"minecraft:white_dye":35,"minecraft:lantern":36,"minecraft:cooked_chicken":2,"minecraft:hopper":40,"minecraft:chainmail_leggings":9,"minecraft:stone_pickaxe":3,"minecraft:anvil":8,"minecraft:netherite_ingot":1,"minecraft:nether_bricks":565,"minecraft:wooden_pickaxe":1,"minecraft:spruce_slab":54,"minecraft:light_blue_dye":2,"minecraft:glowstone":15,"minecraft:light_blue_shulker_box":1,"minecraft:chain":40,"minecraft:fermented_spider_eye":8,"minecraft:diamond_chestplate":2,"minecraft:diamond_sword":2,"minecraft:blue_stained_glass":8,"minecraft:crimson_sign":6,"minecraft:iron_nugget":81,"minecraft:yellow_wool":16,"minecraft:emerald":1542,"minecraft:black_bed":1,"minecraft:spruce_trapdoor":20,"minecraft:spruce_boat":3,"minecraft:white_carpet":231,"minecraft:bread":5,"minecraft:cyan_bed":18,"minecraft:crafting_table":15,"minecraft:spruce_pressure_plate":58,"minecraft:torch":472,"minecraft:white_bed":45,"minecraft:crossbow":1,"minecraft:dropper":4,"minecraft:purple_dye":2,"minecraft:spruce_planks":14955,"minecraft:lectern":6,"minecraft:iron_pickaxe":2},"minecraft:broken":{"minecraft:iron_axe":4,"minecraft:shield":1,"minecraft:netherite_pickaxe":1,"minecraft:stone_axe":5,"minecraft:flint_and_steel":3,"minecraft:diamond_pickaxe":3,"minecraft:diamond_helmet":1,"minecraft:iron_sword":1},"minecraft:dropped":{"minecraft:observer":2,"minecraft:white_dye":25,"minecraft:andesite":101,"minecraft:scrape_pottery_sherd":1,"minecraft:sweet_berries":6,"minecraft:stripped_spruce_log":7,"minecraft:magma_block":2,"minecraft:nether_brick":706,"minecraft:blue_shulker_box":1,"minecraft:bone":1837,"minecraft:glass":386,"minecraft:poppy":359,"minecraft:grindstone":1,"minecraft:cobblestone_slab":2622,"minecraft:tuff_bricks":3,"minecraft:spruce_sign":41,"minecraft:pumpkin":1,"minecraft:cooked_chicken":3,"minecraft:name_tag":1,"minecraft:redstone":379,"minecraft:golden_carrot":22,"minecraft:tuff":25,"minecraft:book":6,"minecraft:scaffolding":9,"minecraft:white_bed":9,"minecraft:spruce_log":611,"minecraft:gunpowder":40,"minecraft:waxed_weathered_copper_bulb":1,"minecraft:gold_ingot":31,"minecraft:rib_armor_trim_smithing_template":1,"minecraft:stone_axe":9,"minecraft:cooked_mutton":4,"minecraft:iron_pickaxe":5,"minecraft:baked_potato":2,"minecraft:purpur_pillar":3,"minecraft:diorite":90,"minecraft:iron_helmet":1,"minecraft:torch":137,"minecraft:stone_sword":6,"minecraft:leather_leggings":5,"minecraft:white_stained_glass":64,"minecraft:bow":12,"minecraft:end_stone":39,"minecraft:bucket":4,"minecraft:raw_copper":55,"minecraft:stone":2854,"minecraft:ominous_bottle":1,"minecraft:melon_slice":1254,"minecraft:sand":73,"minecraft:podzol":1,"minecraft:chest":73,"minecraft:stone_brick_stairs":1,"minecraft:shears":1,"minecraft:ender_chest":1,"minecraft:sculk":1,"minecraft:nether_brick_fence":4,"minecraft:blue_egg":3,"minecraft:lever":2,"minecraft:cracked_stone_bricks":5,"minecraft:decorated_pot":8,"minecraft:bamboo":152,"minecraft:stone_slab":383,"minecraft:cooked_beef":5,"minecraft:iron_block":2128,"minecraft:nether_wart":2,"minecraft:wooden_pickaxe":1,"minecraft:raw_iron":14,"minecraft:waxed_copper_grate":1,"minecraft:crafting_table":3,"minecraft:golden_helmet":6,"minecraft:netherrack":455,"minecraft:cooked_porkchop":8,"minecraft:white_banner":53,"minecraft:iron_axe":13,"minecraft:tripwire_hook":174,"minecraft:iron_shovel":1,"minecraft:glow_berries":1,"minecraft:packed_ice":77,"minecraft:warped_fungus":2,"minecraft:kelp":18,"minecraft:cobbled_deepslate":982,"minecraft:egg":8,"minecraft:spruce_fence_gate":4,"minecraft:sugar_cane":20,"minecraft:clay":1,"minecraft:cobbled_deepslate_stairs":1,"minecraft:iron_nugget":27,"minecraft:chain":10,"minecraft:paper":48,"minecraft:deepslate_iron_ore":1,"minecraft:stone_pickaxe":2,"minecraft:trident":2,"minecraft:shield":10,"minecraft:white_shulker_box":2,"minecraft:chainmail_chestplate":1,"minecraft:redstone_block":44,"minecraft:red_wool":2,"minecraft:white_carpet":25,"minecraft:nether_star":3,"minecraft:string":2296,"minecraft:golden_boots":2,"minecraft:clay_ball":868,"minecraft:purpur_block":1,"minecraft:bread":5,"minecraft:spider_eye":57,"minecraft:firefly_bush":2,"minecraft:snowball":155,"minecraft:guster_pottery_sherd":2,"minecraft:netherite_pickaxe":5,"minecraft:cobblestone":1467,"minecraft:copper_ore":12,"minecraft:spruce_planks":241,"minecraft:leather_boots":6,"minecraft:potion":4,"minecraft:white_wool":428,"minecraft:leather":12,"minecraft:diamond_boots":2,"minecraft:diamond_chestplate":2,"minecraft:chainmail_boots":9,"minecraft:comparator":6,"minecraft:moss_carpet":16,"minecraft:saddle":7,"minecraft:cobbled_deepslate_slab":1,"minecraft:waxed_copper_block":5,"minecraft:cobblestone_wall":4,"minecraft:bone_meal":5,"minecraft:beetroot_seeds":3,"minecraft:netherite_sword":5,"minecraft:stone_button":4,"minecraft:chiseled_tuff_bricks":1,"minecraft:deepslate_tiles":1,"minecraft:beef":10,"minecraft:shulker_box":1,"minecraft:iron_sword":5,"minecraft:spruce_door":2,"minecraft:spruce_fence":196,"minecraft:red_shulker_box":1,"minecraft:axolotl_bucket":2,"minecraft:writable_book":2,"minecraft:stone_stairs":32,"minecraft:purpur_slab":3,"minecraft:piglin_banner_pattern":1,"minecraft:sugar":25,"minecraft:waxed_oxidized_copper_grate":9,"minecraft:brewing_stand":1,"minecraft:crimson_roots":5,"minecraft:ice":72,"minecraft:spruce_button":65,"minecraft:gravel":86,"minecraft:brick":35,"minecraft:ink_sac":1,"minecraft:glowstone":2,"minecraft:cobweb":25,"minecraft:enchanted_book":20,"minecraft:moss_block":33,"minecraft:redstone_lamp":1,"minecraft:nether_bricks":21,"minecraft:crossbow":18,"minecraft:soul_sand":38,"minecraft:filled_map":6,"minecraft:minecart":13,"minecraft:crafter":1,"minecraft:glowstone_dust":21,"minecraft:emerald_block":2,"minecraft:leather_chestplate":3,"minecraft:grass_block":3,"minecraft:spruce_pressure_plate":30,"minecraft:nether_quartz_ore":4,"minecraft:spruce_stairs":28,"minecraft:arrow":11070,"minecraft:spruce_sapling":122,"minecraft:carrot":258,"minecraft:twisting_vines":1,"minecraft:redstone_torch":44,"minecraft:deepslate":4,"minecraft:polished_andesite":74,"minecraft:guster_banner_pattern":1,"minecraft:golden_apple":1,"minecraft:tipped_arrow":5,"minecraft:rotten_flesh":2142,"minecraft:chainmail_leggings":11,"minecraft:iron_chestplate":5,"minecraft:sandstone":22,"minecraft:dirt":437,"minecraft:smooth_stone":2,"minecraft:obsidian":47,"minecraft:golden_chestplate":1,"minecraft:blue_wool":1,"minecraft:oak_fence":2,"minecraft:ender_pearl":1985,"minecraft:emerald":534,"minecraft:rail":234,"minecraft:coal":1433,"minecraft:potato":2264,"minecraft:glass_bottle":12,"minecraft:brown_mushroom":35,"minecraft:stone_brick_slab":48,"minecraft:purple_carpet":2,"minecraft:netherite_axe":1,"minecraft:cookie":3,"minecraft:vine":3,"minecraft:iron_ore":3,"minecraft:azalea":5,"minecraft:blaze_rod":17,"minecraft:diamond_shovel":5,"minecraft:coarse_dirt":2,"minecraft:powered_rail":58,"minecraft:lectern":1,"minecraft:mossy_cobblestone":13,"minecraft:wheat":76,"minecraft:detector_rail":33,"minecraft:basalt":6,"minecraft:chainmail_helmet":1,"minecraft:wheat_seeds":354,"minecraft:iron_ingot":10850,"minecraft:spruce_trapdoor":39,"minecraft:armor_stand":1,"minecraft:polished_tuff":1,"minecraft:light_gray_wool":1,"minecraft:warped_roots":18,"minecraft:oak_log":17,"minecraft:purple_dye":1,"minecraft:diamond_pickaxe":5,"minecraft:dandelion":1,"minecraft:hopper":26,"minecraft:blaze_powder":2,"minecraft:stick":143,"minecraft:deepslate_gold_ore":1,"minecraft:coal_ore":33,"minecraft:phantom_membrane":9,"minecraft:tnt":28,"minecraft:iron_boots":11,"minecraft:fletching_table":1,"minecraft:mossy_stone_bricks":9,"minecraft:leather_helmet":2,"minecraft:totem_of_undying":27,"minecraft:melon_seeds":56,"minecraft:netherite_shovel":1,"minecraft:wooden_hoe":1,"minecraft:pumpkin_seeds":16,"minecraft:diamond_axe":4,"minecraft:spore_blossom":1,"minecraft:bundle":1,"minecraft:firework_rocket":445,"minecraft:iron_hoe":2,"minecraft:cyan_bed":1,"minecraft:gold_block":1,"minecraft:diamond_leggings":1,"minecraft:granite":130,"minecraft:warped_nylium":8,"minecraft:diamond":43,"minecraft:feather":12,"minecraft:golden_sword":1,"minecraft:poisonous_potato":30,"minecraft:pumpkin_pie":43,"minecraft:iron_bars":65,"minecraft:waxed_oxidized_copper":1,"minecraft:water_bucket":1,"minecraft:chiseled_tuff":1,"minecraft:map":3,"minecraft:dragon_head":2,"minecraft:stone_bricks":345,"minecraft:chicken":3,"minecraft:sculk_vein":1,"minecraft:flint":11,"minecraft:diamond_sword":11,"minecraft:lingering_potion":1,"minecraft:big_dripleaf":5,"minecraft:gold_nugget":2,"minecraft:salmon":12,"minecraft:netherite_upgrade_smithing_template":1,"minecraft:wither_skeleton_skull":57,"minecraft:elytra":5,"minecraft:cod":1,"minecraft:magma_cream":18,"minecraft:warped_planks":16},"minecraft:picked_up":{"minecraft:cobblestone_wall":183,"minecraft:enchanting_table":3,"minecraft:sweet_berries":108,"minecraft:smooth_stone_slab":13,"minecraft:cobblestone":5327,"minecraft:shears":2,"minecraft:minecart":166,"minecraft:brick":35,"minecraft:saddle":13,"minecraft:sugar_cane":1315,"minecraft:hopper_minecart":4,"minecraft:bone":1146,"minecraft:cooked_mutton":6,"minecraft:diamond_shovel":17,"minecraft:clay_ball":896,"minecraft:waxed_copper_grate":2,"minecraft:stripped_spruce_log":56,"minecraft:iron_bars":30,"minecraft:iron_sword":5,"minecraft:white_banner":26,"minecraft:blaze_rod":45,"minecraft:emerald":565,"minecraft:chainmail_chestplate":1,"minecraft:deepslate_diamond_ore":2,"minecraft:sugar":19,"minecraft:book":396,"minecraft:purpur_pillar":19,"minecraft:armor_stand":1,"minecraft:ink_sac":18,"minecraft:light_blue_wool":1,"minecraft:chainmail_helmet":1,"minecraft:bow":25,"minecraft:arrow":1140,"minecraft:smooth_basalt":1,"minecraft:iron_ingot":14288,"minecraft:spruce_slab":19,"minecraft:crossbow":11,"minecraft:spore_blossom":2,"minecraft:azalea":5,"minecraft:dandelion":1,"minecraft:firework_rocket":402,"minecraft:nautilus_shell":2,"minecraft:mutton":6,"minecraft:guster_pottery_sherd":3,"minecraft:golden_carrot":14,"minecraft:diamond_leggings":15,"minecraft:iron_chestplate":5,"minecraft:spruce_leaves":211,"minecraft:polished_blackstone_bricks":3,"minecraft:crimson_stem":4,"minecraft:big_dripleaf":5,"minecraft:cobblestone_stairs":45,"minecraft:red_shulker_box":48,"minecraft:oak_log":17,"minecraft:sand":3895,"minecraft:furnace":2,"minecraft:wheat_seeds":865,"minecraft:black_bed":12,"minecraft:iron_ore":6,"minecraft:leather_leggings":5,"minecraft:quartz":97,"minecraft:white_shulker_box":60,"minecraft:egg":8,"minecraft:diamond_sword":19,"minecraft:closed_eyeblossom":1,"minecraft:red_mushroom":2,"minecraft:snowball":269,"minecraft:blast_furnace":1,"minecraft:chiseled_tuff_bricks":1,"minecraft:warped_planks":8,"minecraft:beetroot_seeds":6,"minecraft:chainmail_boots":6,"minecraft:ender_pearl":3903,"minecraft:string":553,"minecraft:golden_sword":2,"minecraft:smithing_table":3,"minecraft:stone_bricks":307,"minecraft:obsidian":384,"minecraft:leather_boots":5,"minecraft:writable_book":13,"minecraft:white_carpet":106,"minecraft:chain":32,"minecraft:iron_helmet":2,"minecraft:comparator":78,"minecraft:warped_fungus":3,"minecraft:ender_chest":126,"minecraft:enchanted_book":27,"minecraft:spruce_sapling":254,"minecraft:iron_block":2003,"minecraft:spruce_fence_gate":10,"minecraft:scrape_pottery_sherd":1,"minecraft:tripwire_hook":909,"minecraft:glowstone":44,"minecraft:flowering_azalea":1,"minecraft:white_bed":73,"minecraft:bucket":13,"minecraft:guster_banner_pattern":1,"minecraft:leather":23,"minecraft:shulker_shell":35,"minecraft:honey_bottle":8,"minecraft:lead":8,"minecraft:brown_mushroom":86,"minecraft:moss_carpet":16,"minecraft:sculk_vein":1,"minecraft:ghast_tear":5,"minecraft:scaffolding":86,"minecraft:porkchop":7,"minecraft:dropper":1,"minecraft:spruce_sign":39,"minecraft:deepslate_lapis_ore":6,"minecraft:stick":303,"minecraft:redstone_torch":63,"minecraft:polished_tuff":1,"minecraft:bamboo":465,"minecraft:turtle_egg":1,"minecraft:diamond_boots":17,"minecraft:moss_block":34,"minecraft:cooked_porkchop":120,"minecraft:twisting_vines":1,"minecraft:iron_axe":5,"minecraft:deepslate":60,"minecraft:cauldron":2,"minecraft:cookie":6,"minecraft:raw_iron":392,"minecraft:shulker_box":125,"minecraft:diamond_chestplate":13,"minecraft:waxed_oxidized_copper_grate":10,"minecraft:mossy_cobblestone":343,"minecraft:detector_rail":39,"minecraft:nether_brick":458,"minecraft:white_dye":4,"minecraft:leather_helmet":2,"minecraft:spruce_door":20,"minecraft:spruce_pressure_plate":34,"minecraft:chest":285,"minecraft:end_rod":10,"minecraft:lectern":535,"minecraft:netherite_sword":6,"minecraft:sculk":8,"minecraft:cobbled_deepslate_slab":2,"minecraft:netherrack":7674,"minecraft:purpur_slab":4,"minecraft:red_wool":2,"minecraft:beacon":3,"minecraft:trident":2,"minecraft:waxed_exposed_copper_bulb":1,"minecraft:stone":24660,"minecraft:gravel":550,"minecraft:jungle_planks":3,"minecraft:bell":12,"minecraft:tuff":25,"minecraft:phantom_membrane":10,"minecraft:redstone_block":132,"minecraft:potato":3260,"minecraft:shield":9,"minecraft:lapis_lazuli":222,"minecraft:jungle_log":1,"minecraft:spruce_stairs":43,"minecraft:activator_rail":54,"minecraft:ominous_bottle":15,"minecraft:trial_key":21,"minecraft:netherite_shovel":1,"minecraft:cobweb":25,"minecraft:oak_planks":3,"minecraft:ice":269,"minecraft:flint_and_steel":1,"minecraft:raw_copper":116,"minecraft:stone_brick_stairs":1,"minecraft:purple_bed":26,"minecraft:rotten_flesh":922,"minecraft:ancient_debris":1,"minecraft:apple":3,"minecraft:fern":1,"minecraft:calcite":2,"minecraft:sponge":17,"minecraft:waxed_weathered_copper_bulb":1,"minecraft:cracked_stone_bricks":11,"minecraft:iron_door":6,"minecraft:tropical_fish":13,"minecraft:poisonous_potato":30,"minecraft:name_tag":3,"minecraft:stone_button":5,"minecraft:polished_andesite":74,"minecraft:brewing_stand":4,"minecraft:glass":712,"minecraft:composter":46,"minecraft:flint":56,"minecraft:purpur_block":25,"minecraft:warped_roots":19,"minecraft:redstone":699,"minecraft:deepslate_tiles":61,"minecraft:music_disc_creator_music_box":1,"minecraft:redstone_lamp":1,"minecraft:flow_banner_pattern":2,"minecraft:glow_berries":1,"minecraft:firefly_bush":4,"minecraft:lantern":18,"minecraft:melon_slice":1449,"minecraft:diamond":182,"minecraft:slime_ball":14,"minecraft:chipped_anvil":1,"minecraft:granite":445,"minecraft:smoker":2,"minecraft:dragon_egg":1,"minecraft:stone_brick_slab":5,"minecraft:deepslate_iron_ore":1,"minecraft:crimson_roots":5,"minecraft:spruce_button":12,"minecraft:flow_armor_trim_smithing_template":1,"minecraft:nether_wart":60,"minecraft:salmon":14,"minecraft:waxed_copper_door":1,"minecraft:packed_ice":1293,"minecraft:powered_rail":203,"minecraft:charcoal":6,"minecraft:spruce_boat":48,"minecraft:cobbled_deepslate_stairs":2,"minecraft:gold_block":1,"minecraft:nether_quartz_ore":8,"minecraft:magma_cream":9,"minecraft:end_stone":566,"minecraft:observer":44,"minecraft:dark_oak_planks":19,"minecraft:enchanted_golden_apple":2,"minecraft:raw_gold":153,"minecraft:stone_sword":4,"minecraft:emerald_block":177,"minecraft:mossy_stone_bricks":10,"minecraft:pale_oak_sign":3,"minecraft:spruce_planks":952,"minecraft:light_blue_shulker_box":5,"minecraft:dirt":14110,"minecraft:basalt":663,"minecraft:blue_egg":4,"minecraft:rail":1253,"minecraft:bone_block":38,"minecraft:blue_wool":1,"minecraft:diamond_helmet":9,"minecraft:iron_shovel":3,"minecraft:golden_boots":2,"minecraft:torch":357,"minecraft:diamond_pickaxe":15,"minecraft:ender_eye":8,"minecraft:bread":14,"minecraft:iron_boots":2,"minecraft:spruce_log":4777,"minecraft:coal":1829,"minecraft:stone_stairs":34,"minecraft:netherite_pickaxe":8,"minecraft:large_fern":1,"minecraft:oak_fence":2,"minecraft:sculk_sensor":2,"minecraft:iron_pickaxe":4,"minecraft:tnt":113,"minecraft:anvil":13,"minecraft:nether_bricks":238,"minecraft:milk_bucket":1,"minecraft:bookshelf":15,"minecraft:hopper":24,"minecraft:waxed_copper_block":7,"minecraft:totem_of_undying":37,"minecraft:poppy":280,"minecraft:cooked_beef":100,"minecraft:nether_star":6,"minecraft:white_wool":280,"minecraft:feather":6,"minecraft:jack_o_lantern":1,"minecraft:potion":24,"minecraft:spruce_fence":446,"minecraft:fletching_table":31,"minecraft:warped_nylium":15,"minecraft:andesite":455,"minecraft:ladder":21,"minecraft:sandstone":103,"minecraft:filled_map":1,"minecraft:vine":3,"minecraft:stone_pressure_plate":56,"minecraft:coal_ore":384,"minecraft:soul_sand":189,"minecraft:podzol":4,"minecraft:diamond_axe":15,"minecraft:carrot":197,"minecraft:soul_soil":5,"minecraft:yellow_carpet":24,"minecraft:breeze_rod":125,"minecraft:gold_nugget":310,"minecraft:stone_slab":840,"minecraft:water_bucket":9,"minecraft:stone_pickaxe":1,"minecraft:cod":1,"minecraft:chiseled_tuff":1,"minecraft:gold_ingot":21,"minecraft:chorus_fruit":14,"minecraft:baked_potato":84,"minecraft:melon_seeds":56,"minecraft:pink_banner":1,"minecraft:glow_ink_sac":14,"minecraft:golden_apple":44,"minecraft:waxed_oxidized_cut_copper":1,"minecraft:copper_ore":147,"minecraft:dragon_head":3,"minecraft:black_wool":2,"minecraft:chicken":2,"minecraft:clay":1,"minecraft:leather_chestplate":3,"minecraft:golden_chestplate":1,"minecraft:repeater":17,"minecraft:cooked_chicken":118,"minecraft:grindstone":13,"minecraft:kelp":202,"minecraft:cobbled_deepslate":1693,"minecraft:cyan_bed":39,"minecraft:spruce_wood":27,"minecraft:glowstone_dust":191,"minecraft:pumpkin_seeds":26,"minecraft:stone_axe":6,"minecraft:end_stone_bricks":4,"minecraft:amethyst_block":2,"minecraft:wheat":270,"minecraft:tuff_bricks":4,"minecraft:map":5,"minecraft:damaged_anvil":3,"minecraft:gunpowder":141,"minecraft:pumpkin_pie":15,"minecraft:blue_shulker_box":76,"minecraft:elytra":12,"minecraft:nether_gold_ore":3,"minecraft:spruce_trapdoor":392,"minecraft:blackstone":15,"minecraft:blaze_powder":2,"minecraft:chainmail_leggings":3,"minecraft:coarse_dirt":14,"minecraft:white_stained_glass":2,"minecraft:magma_block":873,"minecraft:lever":123,"minecraft:smooth_stone":4,"minecraft:light_gray_wool":1,"minecraft:blue_ice":26,"minecraft:lodestone":1,"minecraft:leaf_litter":4,"minecraft:nether_brick_fence":5,"minecraft:deepslate_gold_ore":8,"minecraft:grass_block":15,"minecraft:sticky_piston":1,"minecraft:pumpkin":36,"minecraft:diamond_block":2,"minecraft:piston":256,"minecraft:spider_eye":73,"minecraft:coal_block":10,"minecraft:bone_meal":17,"minecraft:netherite_axe":1,"minecraft:tipped_arrow":57,"minecraft:diorite":227,"minecraft:flower_pot":3,"minecraft:golden_helmet":6,"minecraft:crafting_table":86,"minecraft:ominous_trial_key":7,"minecraft:decorated_pot":12,"minecraft:warped_stem":2,"minecraft:bundle":4,"minecraft:beef":36,"minecraft:wither_skeleton_skull":4,"minecraft:wind_charge":53,"minecraft:cobblestone_slab":2017,"minecraft:glass_bottle":15,"minecraft:crafter":9,"minecraft:blue_bed":6,"minecraft:purple_shulker_box":46,"minecraft:waxed_oxidized_copper":2,"minecraft:iron_hoe":1,"minecraft:paper":122,"minecraft:purple_carpet":10,"minecraft:gray_wool":1},"minecraft:killed":{"minecraft:fox":1,"minecraft:pig":4,"minecraft:piglin_brute":3,"minecraft:piglin":33,"minecraft:vindicator":54,"minecraft:ravager":5,"minecraft:bat":4,"minecraft:silverfish":44,"minecraft:wandering_trader":4,"minecraft:cat":1,"minecraft:salmon":8,"minecraft:shulker":48,"minecraft:zombie":280,"minecraft:glow_squid":4,"minecraft:zombie_villager":8,"minecraft:chicken":5,"minecraft:squid":5,"minecraft:drowned":16,"minecraft:cow":35,"minecraft:endermite":1,"minecraft:slime":3,"minecraft:pillager":142,"minecraft:skeleton":165,"minecraft:phantom":22,"minecraft:tropical_fish":8,"minecraft:iron_golem":56,"minecraft:witch":20,"minecraft:villager":10,"minecraft:cod":1,"minecraft:spider":53,"minecraft:ender_dragon":1,"minecraft:wither":3,"minecraft:husk":80,"minecraft:wither_skeleton":58,"minecraft:trader_llama":7,"minecraft:creeper":88,"minecraft:hoglin":1,"minecraft:sheep":3,"minecraft:enderman":11343,"minecraft:evoker":16,"minecraft:polar_bear":2,"minecraft:magma_cube":30,"minecraft:vex":27,"minecraft:ghast":25,"minecraft:breeze":14,"minecraft:blaze":95}},"DataVersion":4325}